Metadata-Version: 1.0
Name: udacityTestDistributionsxx
Version: 0.1
Summary: Gaussian distributions and binomial distribution
Home-page: UNKNOWN
Author: mohit 
Author-email: mohitahlawat.2001.ma@gmail.com
License: UNKNOWN
Platform: UNKNOWN
